MANIFEST.in
README.rst
setup.py
nextkg_api/__init__.py
nextkg_api/client.py
nextkg_api/data_models.py
nextkg_api/utils.py
nextkg_api.egg-info/PKG-INFO
nextkg_api.egg-info/SOURCES.txt
nextkg_api.egg-info/dependency_links.txt
nextkg_api.egg-info/not-zip-safe
nextkg_api.egg-info/requires.txt
nextkg_api.egg-info/top_level.txt
requirements/docs.txt
tests/__init__.py