Metadata-Version: 2.1
Name: nextkg-api
Version: 0.1
Summary: NextKG API
Home-page: UNKNOWN
License: UNKNOWN
Platform: UNKNOWN
Requires-Python: >=3.6
